atai_pdf_tool/__init__.py
atai_pdf_tool/cli.py
atai_pdf_tool/parser.py
atai_pdf_tool-0.1.1.dist-info/LICENSE
atai_pdf_tool-0.1.1.dist-info/METADATA
atai_pdf_tool-0.1.1.dist-info/WHEEL
atai_pdf_tool-0.1.1.dist-info/entry_points.txt
atai_pdf_tool-0.1.1.dist-info/top_level.txt
atai_pdf_tool-0.1.1.dist-info/RECORD
