Metadata-Version: 2.2
Name: atai-pdf-tool
Version: 0.1.1
Summary: A tool for parsing and extracting text from PDF files with OCR capabilities
Home-page: https://github.com/AtomGradient/atai-pdf-tool
Author: AtomGradient
Author-email: AtomGradient <alex@atomgradient.com>
License: MIT
Project-URL: Homepage, https://github.com/AtomGradient/atai-pdf-tool
Project-URL: Bug Tracker, https://github.com/AtomGradient/atai-pdf-tool/issues
Keywords: pdf,ocr,text-extraction,document-processing
Classifier: Programming Language :: Python :: 3
Classifier: License :: OSI Approved :: MIT License
Classifier: Operating System :: OS Independent
Requires-Python: >=3.6
License-File: LICENSE
Requires-Dist: PyPDF2
Requires-Dist: PyMuPDF
Requires-Dist: easyocr
Requires-Dist: tqdm
Dynamic: author
Dynamic: home-page
Dynamic: requires-python
